ufcscraper/__init__.py
ufcscraper/base.py
ufcscraper/catch_weights.py
ufcscraper/event_scraper.py
ufcscraper/fight_scraper.py
ufcscraper/fighter_names.py
ufcscraper/fighter_scraper.py
ufcscraper/odds_scraper/__init__.py
ufcscraper/odds_scraper/bet365_odds_reader.py
ufcscraper/odds_scraper/bfo_scraper.py
ufcscraper/replacement_scraper.py
ufcscraper/scripts/__init__.py
ufcscraper/scripts/check_missing_records.py
ufcscraper/scripts/consolidate_bet365_odds.py
ufcscraper/scripts/read_bet365_odds.py
ufcscraper/scripts/scrape_bestfightodds_data.py
ufcscraper/scripts/scrape_ufcstats_data.py
ufcscraper/ufc_scraper.py
ufcscraper/utils.py
ufcscraper-1.1.0.dist-info/METADATA
ufcscraper-1.1.0.dist-info/WHEEL
ufcscraper-1.1.0.dist-info/entry_points.txt
ufcscraper-1.1.0.dist-info/RECORD
